{
  "collectionName": "components_blocks_dynamic_heroes",
  "info": {
    "displayName": "Dynamic Hero",
    "icon": "picture"
  },
  "options": {},
  "attributes": {
    "title": {
      "type": "string",
      "required": false
    },
    "description": {
      "type": "text"
    },
    "media": {
      "type": "media",
      "multiple": true,
      "required": false,
      "allowedTypes": [
        "images",
        "videos"
      ]
    },
    "buttons": {
      "type": "component",
      "component": "shared.button",
      "repeatable": true,
      "max": 2
    },
    "tags": {
      "type": "component",
      "component": "shared.tag",
      "repeatable": true
    }
  }
}
